notifications/__init__.py
notifications/admin.py
notifications/app_settings.py
notifications/apps.py
notifications/cron.py
notifications/expo_utils.py
notifications/helpers.py
notifications/models.py
notifications/serializers.py
notifications/settings.py
notifications/signals.py
notifications/urls.py
notifications/utils.py
notifications/views.py
notifications/base/__init__.py
notifications/base/admin.py
notifications/base/models.py
notifications/locale/id/LC_MESSAGES/django.po
notifications/locale/ru/LC_MESSAGES/django.po
notifications/management/__init__.py
notifications/management/commands/__init__.py
notifications/management/commands/delete_old_notifications.py
notifications/migrations/0001_initial.py
notifications/migrations/__init__.py
notifications/templates/notifications/list.html
notifications/templates/notifications/notice.html
notifications/templates/notifications/test_tags.html
notifications/templatetags/__init__.py
notifications/templatetags/notifications_tags.py
notifications/tests/__init__.py
notifications/tests/settings.py
notifications/tests/tests.py
notifications/tests/urls.py
notifications/tests/views.py
notifications/tests/sample_notifications/__init__.py
notifications/tests/sample_notifications/admin.py
notifications/tests/sample_notifications/apps.py
notifications/tests/sample_notifications/models.py
notifications/tests/sample_notifications/tests.py
notifications/tests/sample_notifications/migrations/0001_initial.py
notifications/tests/sample_notifications/migrations/__init__.py
notifications/tests/sample_notifications/templatetags/__init__.py
notifications/tests/sample_notifications/templatetags/notifications_tags.py
notifications/tests/templates/test_live.html
notifications/tests/test_models/models.py
notifications/tests/test_models/migrations/0001_initial.py
notifications/tests/test_models/migrations/__init__.py
django_notifications_pro-1.8.0.dist-info/AUTHORS.txt
django_notifications_pro-1.8.0.dist-info/LICENSE.txt
django_notifications_pro-1.8.0.dist-info/METADATA
django_notifications_pro-1.8.0.dist-info/WHEEL
django_notifications_pro-1.8.0.dist-info/top_level.txt
django_notifications_pro-1.8.0.dist-info/RECORD
