Metadata-Version: 2.1
Name: django-notifications-pro
Version: 1.8.0
Summary: GitHub notifications alike app for Django with expo push notifications
Home-page: https://github.com/nachoborrelli/django-notifications
License: MIT
Keywords: django notifications github action event stream expo push viewset cron crontab
Classifier: Development Status :: 5 - Production/Stable
Classifier: Environment :: Web Environment
Classifier: Framework :: Django
Classifier: Intended Audience :: Developers
Classifier: License :: OSI Approved :: BSD License
Classifier: Operating System :: OS Independent
Classifier: Framework :: Django
Classifier: Framework :: Django :: 3.2
Classifier: Framework :: Django :: 4.0
Classifier: Framework :: Django :: 4.1
Classifier: Programming Language :: Python
Classifier: Programming Language :: Python :: 3
Classifier: Programming Language :: Python :: 3.7
Classifier: Programming Language :: Python :: 3.8
Classifier: Programming Language :: Python :: 3.9
Classifier: Programming Language :: Python :: 3.10
Classifier: Programming Language :: Python :: 3.11
Classifier: Topic :: Utilities
License-File: LICENSE.txt
License-File: AUTHORS.txt
Requires-Dist: django >=3.2
Requires-Dist: django-model-utils >=3.1.0
Requires-Dist: jsonfield >=2.1.0
Requires-Dist: pytz
Requires-Dist: swapper
Requires-Dist: pandas >=2.2.0
Requires-Dist: requests >=2.30
Provides-Extra: crontab
Requires-Dist: django-crontab ~=0.7.1 ; extra == 'crontab'
Provides-Extra: expo
Requires-Dist: exponent-server-sdk ~=2.0.0 ; extra == 'expo'
